{
    "github": [
        "aternosorg"
    ],
    "patreon": [
        "Alister",
        "Andrean Olgo",
        "Cherriesaurus",
        "Michael W. S.",
        "Nahuel Fernandez",
        "Shana Gitnick",
        "Tyler Behl"
    ],
    "combined": [
        "Alister",
        "Andrean Olgo",
        "aternosorg",
        "Cherriesaurus",
        "Michael W. S.",
        "Nahuel Fernandez",
        "Shana Gitnick",
        "Tyler Behl"
    ],
    "combined_specific": {
        "Alister": "Patreon",
        "Andrean Olgo": "Patreon",
        "aternosorg": "Github Sponsors",
        "Cherriesaurus": "Patreon",
        "Michael W. S.": "Patreon",
        "Nahuel Fernandez": "Patreon",
        "Shana Gitnick": "Patreon",
        "Tyler Behl": "Patreon"
    }
}